ghost_blog_smart/__init__.py
ghost_blog_smart/blog_post_refine_prompt.py
ghost_blog_smart/blog_to_image_prompt.py
ghost_blog_smart/clean_imagen_generator.py
ghost_blog_smart/client.py
ghost_blog_smart/main_functions.py
ghost_blog_smart/post_management.py
ghost_blog_smart/replicate_flux_generator.py
ghost_blog_smart/smart_gateway.py
tests/__init__.py
tests/conftest.py
tests/test_api.py
ghost_blog_smart-1.1.3.dist-info/METADATA
ghost_blog_smart-1.1.3.dist-info/WHEEL
ghost_blog_smart-1.1.3.dist-info/top_level.txt
ghost_blog_smart-1.1.3.dist-info/RECORD
