Metadata-Version: 2.1
Name: ghost-blog-smart
Version: 1.1.3
Summary: A powerful Python library and REST API for creating Ghost CMS blog posts with AI-powered features including Flask API and Docker deployment
Home-page: https://github.com/preangelleo/ghost-blog-smart
Author: leowang.net
Author-email: me@leowang.net
Project-URL: Bug Reports, https://github.com/preangelleo/ghost-blog-smart/issues
Project-URL: Source, https://github.com/preangelleo/ghost-blog-smart
Project-URL: Documentation, https://github.com/preangelleo/ghost-blog-smart#readme
Keywords: ghost cms blog ai gemini imagen markdown jwt api content-management
Classifier: Development Status :: 5 - Production/Stable
Classifier: Intended Audience :: Developers
Classifier: Topic :: Software Development :: Libraries :: Python Modules
Classifier: Topic :: Internet :: WWW/HTTP :: Dynamic Content :: Content Management System
Classifier: License :: OSI Approved :: MIT License
Classifier: Programming Language :: Python :: 3
Classifier: Programming Language :: Python :: 3.7
Classifier: Programming Language :: Python :: 3.8
Classifier: Programming Language :: Python :: 3.9
Classifier: Programming Language :: Python :: 3.10
Classifier: Programming Language :: Python :: 3.11
Classifier: Operating System :: OS Independent
Requires-Python: >=3.7
Requires-Dist: pypinyin>=0.50.0
Requires-Dist: google-generativeai>=0.8.0
Requires-Dist: markdownify>=0.11.6
Requires-Dist: markdown-it-py>=3.0.0
Requires-Dist: markdown>=3.5.0
Requires-Dist: requests>=2.31.0
Requires-Dist: PyJWT>=2.8.0
Requires-Dist: python-dotenv>=1.0.0
Requires-Dist: google-genai>=1.0.0
Requires-Dist: Pillow>=10.0.0
Requires-Dist: replicate>=1.0.0
Provides-Extra: dev
Requires-Dist: pytest>=7.0; extra == "dev"
Requires-Dist: black>=22.0; extra == "dev"
Requires-Dist: flake8>=4.0; extra == "dev"
Requires-Dist: twine>=4.0; extra == "dev"
Requires-Dist: wheel>=0.37; extra == "dev"
Requires-Dist: setuptools>=65.0; extra == "dev"
